upysize/.gitignore
upysize/__init__.py
upysize/__main__.py
upysize/strategies/__init__.py
upysize/strategies/constants_local_only.py
upysize/strategies/constants_no_const.py
upysize/strategies/function_inline.py
upysize/strategies/helpers.py
upysize/strategies/if_else_assignment.py
upysize/strategies/import_global_cache.py
upysize/strategies/import_one_function.py
upysize/strategies/import_type_only.py
upysize/strategies/keyword_arguments.py
upysize/strategies/local_cache_attribute.py
upysize/strategies/local_cache_global.py
upysize/strategies/small_classes.py
upysize-0.1.0.dist-info/entry_points.txt
upysize-0.1.0.dist-info/WHEEL
upysize-0.1.0.dist-info/METADATA
upysize-0.1.0.dist-info/RECORD
