Metadata-Version: 2.1
Name: upysize
Version: 0.1.0
Summary: Tool to help decrease compiled size of micropython code
Home-page: https://github.com/grdddj/upysize
License: MIT
Keywords: micropython,code size
Author: SatoshiLabs
Author-email: info@satoshilabs.com
Requires-Python: >=3.9,<4.0
Classifier: License :: OSI Approved :: MIT License
Classifier: Programming Language :: Python :: 3
Classifier: Programming Language :: Python :: 3.10
Classifier: Programming Language :: Python :: 3.9
Requires-Dist: click (>=8.1.3,<9.0.0)
Requires-Dist: typing-extensions
Project-URL: Repository, https://github.com/grdddj/upysize
